minesweeper/__init__.py
minesweeper/__main__.py
minesweeper/config.py
minesweeper/assets/__init__.py
minesweeper/assets/colors.py
minesweeper/assets/fonts/Retro.ttf
minesweeper/assets/fonts/Sonic1.ttf
minesweeper/assets/sounds/click.wav
minesweeper/assets/sounds/flag.wav
minesweeper/assets/sounds/lose.wav
minesweeper/assets/sounds/win.wav
minesweeper/assets/sprites/blank-block.png
minesweeper/assets/sprites/block.png
minesweeper/assets/sprites/bomb-block.png
minesweeper/assets/sprites/bomb-explode.png
minesweeper/assets/sprites/bomb.png
minesweeper/assets/sprites/clock.png
minesweeper/assets/sprites/flag.png
minesweeper/assets/sprites/logo.png
minesweeper/assets/sprites/menu_background.png
minesweeper/assets/sprites/question.png
minesweeper/assets/sprites/select-block.png
minesweeper/assets/sprites/warn1.png
minesweeper/assets/sprites/warn2.png
minesweeper/assets/sprites/warn3.png
minesweeper/assets/sprites/warn4.png
minesweeper/assets/sprites/warn5.png
minesweeper/assets/sprites/warn6.png
minesweeper/assets/sprites/warn7.png
minesweeper/assets/sprites/warn8.png
minesweeper/controller/__init__.py
minesweeper/controller/controller.py
minesweeper/model/__init__.py
minesweeper/model/cell_model.py
minesweeper/model/game_model.py
minesweeper/model/records.json
minesweeper/utils/__init__.py
minesweeper/utils/get_path.py
minesweeper/view/__init__.py
minesweeper/view/main_view.py
minesweeper/view/elements/__init__.py
minesweeper/view/elements/button.py
minesweeper/view/elements/cell.py
minesweeper/view/elements/image.py
minesweeper/view/elements/label.py
minesweeper/view/elements/rectangle.py
minesweeper/view/elements/text_object.py
minesweeper/view/views/__init__.py
minesweeper/view/views/game_view.py
minesweeper/view/views/menu_view.py
minesweeper/view/views/records_view.py
minesweeper/view/views/view.py
minesweeper_mvc-1.1.0.dist-info/LICENSE
minesweeper_mvc-1.1.0.dist-info/METADATA
minesweeper_mvc-1.1.0.dist-info/WHEEL
minesweeper_mvc-1.1.0.dist-info/entry_points.txt
minesweeper_mvc-1.1.0.dist-info/top_level.txt
minesweeper_mvc-1.1.0.dist-info/RECORD
