Metadata-Version: 2.1
Name: minesweeper-mvc
Version: 1.1.0
Summary: This simple implementation of the minesweeper game is done in Python using the pygame game library and the MVC pattern. 
Author: Ilya Kalinin
Author-email: gerrux@yandex.ru
License: MIT
Keywords: minesweeper game pygame
Classifier: Development Status :: 4 - Beta
Classifier: Intended Audience :: End Users/Desktop
Classifier: License :: OSI Approved :: MIT License
Requires-Python: >=3.6
License-File: LICENSE
Requires-Dist: pygame >=2.1.2
